pyuncertainnumber/__init__.py
pyuncertainnumber/console.py
pyuncertainnumber/decorator.py
pyuncertainnumber/gutils.py
pyuncertainnumber/calibration/__init__.py
pyuncertainnumber/calibration/calibration.py
pyuncertainnumber/calibration/epistemic_filter.py
pyuncertainnumber/calibration/iterative_filtering.py
pyuncertainnumber/calibration/knn.py
pyuncertainnumber/calibration/mcmc.py
pyuncertainnumber/calibration/pdfs.py
pyuncertainnumber/calibration/tmcmc.py
pyuncertainnumber/calibration/utils_bayesian.py
pyuncertainnumber/calibration/data_peeling/__init__.py
pyuncertainnumber/calibration/data_peeling/examples.py
pyuncertainnumber/calibration/data_peeling/fuzzy.py
pyuncertainnumber/calibration/data_peeling/peeling.py
pyuncertainnumber/calibration/data_peeling/plots.py
pyuncertainnumber/calibration/data_peeling/scenario.py
pyuncertainnumber/calibration/data_peeling/time.py
pyuncertainnumber/characterisation/__init__.py
pyuncertainnumber/characterisation/check.py
pyuncertainnumber/characterisation/config.py
pyuncertainnumber/characterisation/core.py
pyuncertainnumber/characterisation/multiple_UN.py
pyuncertainnumber/characterisation/stats.py
pyuncertainnumber/characterisation/un_fields.py
pyuncertainnumber/characterisation/uncertainNumber.py
pyuncertainnumber/characterisation/utils.py
pyuncertainnumber/nlp/__init__.py
pyuncertainnumber/nlp/language_parsing.py
pyuncertainnumber/nlp/params.py
pyuncertainnumber/opt/__init__.py
pyuncertainnumber/opt/bo.py
pyuncertainnumber/opt/ga.py
pyuncertainnumber/opt/get_range.py
pyuncertainnumber/pba/__init__.py
pyuncertainnumber/pba/aggregation.py
pyuncertainnumber/pba/cbox.py
pyuncertainnumber/pba/cbox_constructor.py
pyuncertainnumber/pba/constructors.py
pyuncertainnumber/pba/context.py
pyuncertainnumber/pba/core.py
pyuncertainnumber/pba/dependency.py
pyuncertainnumber/pba/distributions.py
pyuncertainnumber/pba/dss.py
pyuncertainnumber/pba/ecdf.py
pyuncertainnumber/pba/imprecise.py
pyuncertainnumber/pba/mixins.py
pyuncertainnumber-0.1.4.dist-info/licenses/LICENSE
pyuncertainnumber-0.1.4.dist-info/METADATA
pyuncertainnumber-0.1.4.dist-info/WHEEL
pyuncertainnumber-0.1.4.dist-info/top_level.txt
pyuncertainnumber-0.1.4.dist-info/RECORD
