Metadata-Version: 2.4
Name: pyuncertainnumber
Version: 0.1.4
Summary: Rigorous computation with Uncertain Number in Python
Author-email: "(Leslie) Yu Chen" <leslie.yuchen666@gmail.com>, Roberto Rocchetta <roberto.rocchetta88@gmail.com>, Marco de Angelis <marco.de-angelis@strath.ac.uk>, Scott Ferson <sandp8@gmail.com>, Ioanna Ioannou <Ioanna.Ioannou@liverpool.ac.uk>
Maintainer-email: "(Leslie) Yu Chen" <leslie.yuchen666@gmail.com>
License: MIT License
Project-URL: Documentation, https://pyuncertainnumber.readthedocs.io/en/latest/index.html
Project-URL: Homepage, https://github.com/leslieDLcy/PyUncertainNumber
Requires-Python: >=3.11
License-File: LICENSE
Requires-Dist: matplotlib
Requires-Dist: numpy==1.26.4
Requires-Dist: pandas
Requires-Dist: seaborn
Requires-Dist: Pint
Requires-Dist: pymongo
Requires-Dist: pymoo
Requires-Dist: rich
Requires-Dist: scipy<1.15.2,>=1.15
Requires-Dist: tqdm
Requires-Dist: bayesian-optimization
Requires-Dist: geneticalgorithm
Requires-Dist: statsmodels<0.15,>=0.14
Requires-Dist: jax==0.4.35
Requires-Dist: SALib
Requires-Dist: json5
Provides-Extra: test
Requires-Dist: pytest; extra == "test"
Dynamic: license-file
